{
  "runId": "2026-05-20T05-18-43-731",
  "scenarios": [
    {
      "name": "Sign-out button is visible in the navigation bar on the Dashboard",
      "outcome": "PASS",
      "class": "PASS",
      "confidence": "high",
      "rationale": "Sign out button rendered in the navigation bar on / for the authenticated regular user."
    },
    {
      "name": "Sign-out button is visible on a non-Dashboard authenticated page",
      "outcome": "PASS",
      "class": "PASS",
      "confidence": "high",
      "rationale": "Sign out button rendered on /profile — confirms AC-0's 'always visible' clause across authenticated routes."
    },
    {
      "name": "Clicking Sign out redirects to the login page",
      "outcome": "PASS",
      "class": "PASS",
      "confidence": "high",
      "rationale": "Clicking the Sign out button navigated to /login as required by AC-1."
    },
    {
      "name": "Refresh token is invalidated immediately after logout",
      "outcome": "FAIL",
      "class": "REAL_BUG",
      "confidence": "high",
      "rationale": "After UI logout, POST /api/v1/auth/refresh with the pre-logout refresh_token returns HTTP 200 (expected 4xx). AC-2 \"Refresh token is immediately invalidated\" is not met server-side — client redirects to /login but the refresh token remains valid. Reproduces the prior run's REAL_BUG classification (2026-05-19T16:51:55Z); spec.ts and feature_hash unchanged since."
    },
    {
      "name": "Old access token cannot be reused after logout",
      "outcome": "FAIL",
      "class": "REAL_BUG",
      "confidence": "high",
      "rationale": "After UI logout, GET /api/v1/auth/me with the pre-logout access_token returns HTTP 200 (expected 401). AC-3 \"Old access tokens cannot be reused after logout\" is not met server-side. Reproduces the prior run's REAL_BUG classification."
    }
  ],
  "scenarioCounts": { "total": 5, "passed": 3, "failed": 2, "skipped": 0 }
}
